SirvPy/Sirv.py
SirvPy/__init__.py
SirvPy/access_token.txt
SirvPy/file_handling.py
SirvPy/token_timestamp.txt
SirvPy-1.3.dist-info/LICENSE
SirvPy-1.3.dist-info/METADATA
SirvPy-1.3.dist-info/WHEEL
SirvPy-1.3.dist-info/top_level.txt
SirvPy-1.3.dist-info/RECORD
