Metadata-Version: 2.1
Name: SirvPy
Version: 1.3
Summary: A python library for the Sirv REST API
Home-page: https://github.com/TechniCollins/SirvPy
Author: TechniCollins
Author-email: technicollins.business@gmail.com
License: UNKNOWN
Platform: UNKNOWN
Classifier: Programming Language :: Python :: 3
Classifier: License :: OSI Approved :: MIT License
Classifier: Operating System :: OS Independent
Requires-Python: >=3.8
Requires-Dist: requests
